odoo/addons/contract_invoice_auto_validate/README.rst
odoo/addons/contract_invoice_auto_validate/__init__.py
odoo/addons/contract_invoice_auto_validate/__manifest__.py
odoo/addons/contract_invoice_auto_validate/i18n/contract_invoice_auto_validate.pot
odoo/addons/contract_invoice_auto_validate/models/__init__.py
odoo/addons/contract_invoice_auto_validate/models/contract_contract.py
odoo/addons/contract_invoice_auto_validate/readme/CONTRIBUTORS.rst
odoo/addons/contract_invoice_auto_validate/readme/DESCRIPTION.rst
odoo/addons/contract_invoice_auto_validate/readme/USAGE.rst
odoo/addons/contract_invoice_auto_validate/static/description/icon.png
odoo/addons/contract_invoice_auto_validate/static/description/index.html
odoo/addons/contract_invoice_auto_validate/tests/__init__.py
odoo/addons/contract_invoice_auto_validate/tests/test_contract_invoice_auto_validate.py
odoo12_addon_contract_invoice_auto_validate-12.0.1.0.0.99.dev3.dist-info/METADATA
odoo12_addon_contract_invoice_auto_validate-12.0.1.0.0.99.dev3.dist-info/WHEEL
odoo12_addon_contract_invoice_auto_validate-12.0.1.0.0.99.dev3.dist-info/top_level.txt
odoo12_addon_contract_invoice_auto_validate-12.0.1.0.0.99.dev3.dist-info/RECORD
